address_extractor/__init__.py
address_extractor/__main__.py
address_extractor-0.1.0.post1.dist-info/DESCRIPTION.rst
address_extractor-0.1.0.post1.dist-info/entry_points.txt
address_extractor-0.1.0.post1.dist-info/METADATA
address_extractor-0.1.0.post1.dist-info/metadata.json
address_extractor-0.1.0.post1.dist-info/RECORD
address_extractor-0.1.0.post1.dist-info/top_level.txt
address_extractor-0.1.0.post1.dist-info/WHEEL
