Metadata-Version: 2.0
Name: address-extractor
Version: 0.1.0.post1
Summary: A script to extract US-style street addresses from a text file.
Home-page: https://github.com/scolby33/address_extractor
Author: Scott Colby
Author-email: scolby33@gmail.com
License: MIT License
Keywords: addresses,mailing
Platform: UNKNOWN
Classifier: Development Status :: 4 - Beta
Classifier: Environment :: Console
Classifier: Intended Audience :: End Users/Desktop
Classifier: License :: OSI Approved :: MIT License
Classifier: Programming Language :: Python :: 3.5
Classifier: Topic :: Office/Business
Requires-Dist: usaddress
